{
  "index_name": "ef16996d-f298-4f48-8eb0-00f58ea81612",
  "title": "Karnataka Gross State Domestic Product at Factor Cost by Industry of Origin at Current Prices - From 2004-05 to 2013-14 (as on 01.08.2014)",
  "desc": "Karnataka Gross State Domestic Product at Factor Cost by Industry of Origin at Current Prices - From 2004-05 to 2013-14 (as on 01.08.2014)",
  "org_type": "Central",
  "org": [
    "Ministry of Statistics and Programme Implementation"
  ],
  "sector": [
    "Finance",
    "Economy",
    "Statistics"
  ],
  "source": "data.gov.in",
  "catalog_uuid": "512c247a-2a2e-49a2-8538-8d10250439ae",
  "visualizable": "0",
  "active": "1",
  "created": 1651660847,
  "updated": 1652328659,
  "created_date": "2022-05-04T12:40:47Z",
  "updated_date": "2022-05-12T09:40:59Z",
  "external_ws": 0,
  "external_ws_url": "",
  "target_bucket": {
    "index": "api",
    "type": "512c247a-2a2e-49a2-8538-8d10250439ae",
    "field": "ef16996d-f298-4f48-8eb0-00f58ea81612"
  },
  "field": [
    {
      "id": "category",
      "name": "Category",
      "type": "keyword"
    },
    {
      "id": "sector",
      "name": "Sector",
      "type": "keyword"
    },
    {
      "id": "__2004_05",
      "name": "2004-05",
      "type": "double"
    },
    {
      "id": "__2005_06",
      "name": "2005-06",
      "type": "double"
    },
    {
      "id": "__2006_07",
      "name": "2006-07",
      "type": "double"
    },
    {
      "id": "__2007_08",
      "name": "2007-08",
      "type": "double"
    },
    {
      "id": "__2008_09",
      "name": "2008-09",
      "type": "double"
    },
    {
      "id": "__2009_10",
      "name": "2009-10",
      "type": "double"
    },
    {
      "id": "__2010_11",
      "name": "2010-11",
      "type": "double"
    },
    {
      "id": "__2011_12",
      "name": "2011-12",
      "type": "double"
    },
    {
      "id": "__2012_13",
      "name": "2012-13",
      "type": "double"
    },
    {
      "id": "__2013_14",
      "name": "2013-14",
      "type": "double"
    }
  ],
  "message": "Resource lists",
  "version": "2.2.0",
  "status": "ok",
  "total": 23,
  "count": 23,
  "limit": "999",
  "offset": "0",
  "records": [
    {
      "category": "Ag & Allied",
      "sector": "Agriculture",
      "__2004_05": 2645533,
      "__2005_06": 3258811,
      "__2006_07": 3326756,
      "__2007_08": 3902162,
      "__2008_09": 4061267,
      "__2009_10": 4679203,
      "__2010_11": 6244015,
      "__2011_12": 6198503,
      "__2012_13": 6652655,
      "__2013_14": 6491849
    },
    {
      "category": "Ag & Allied",
      "sector": "Forestry & logging",
      "__2004_05": 410446,
      "__2005_06": 487580,
      "__2006_07": 517723,
      "__2007_08": 618246,
      "__2008_09": 712737,
      "__2009_10": 609929,
      "__2010_11": 884717,
      "__2011_12": 864026,
      "__2012_13": 1146457,
      "__2013_14": 1339682
    },
    {
      "category": "Ag & Allied",
      "sector": "Fishing",
      "__2004_05": 63005,
      "__2005_06": 83343,
      "__2006_07": 94182,
      "__2007_08": 91134,
      "__2008_09": 149603,
      "__2009_10": 175104,
      "__2010_11": 246464,
      "__2011_12": 272350,
      "__2012_13": 319340,
      "__2013_14": 323791
    },
    {
      "category": "Ag & Allied",
      "sector": "Total",
      "__2004_05": 3118984,
      "__2005_06": 3829735,
      "__2006_07": 3938661,
      "__2007_08": 4611542,
      "__2008_09": 4923607,
      "__2009_10": 5464235,
      "__2010_11": 7375196,
      "__2011_12": 7334879,
      "__2012_13": 8118453,
      "__2013_14": 8155322
    },
    {
      "category": "Mining & quarrying",
      "sector": "Mining & quarrying",
      "__2004_05": 192570,
      "__2005_06": 231563,
      "__2006_07": 293582,
      "__2007_08": 536287,
      "__2008_09": 538106,
      "__2009_10": 463971,
      "__2010_11": 762667,
      "__2011_12": 400512,
      "__2012_13": 399781,
      "__2013_14": 417002
    },
    {
      "category": "Manufacturing",
      "sector": "Total",
      "__2004_05": 3059886,
      "__2005_06": 3338519,
      "__2006_07": 4367417,
      "__2007_08": 4845468,
      "__2008_09": 5776686,
      "__2009_10": 5529466,
      "__2010_11": 6262942,
      "__2011_12": 7000882,
      "__2012_13": 7462699,
      "__2013_14": 7853302
    },
    {
      "category": "Manufacturing",
      "sector": "Registered",
      "__2004_05": 2378054,
      "__2005_06": 2576571,
      "__2006_07": 3486371,
      "__2007_08": 3833634,
      "__2008_09": 4538212,
      "__2009_10": 4346206,
      "__2010_11": 4897668,
      "__2011_12": 5475337,
      "__2012_13": 5844546,
      "__2013_14": 6183986
    },
    {
      "category": "Manufacturing",
      "sector": "Unregistered",
      "__2004_05": 681833,
      "__2005_06": 761948,
      "__2006_07": 881046,
      "__2007_08": 1011834,
      "__2008_09": 1238474,
      "__2009_10": 1183260,
      "__2010_11": 1365274,
      "__2011_12": 1525545,
      "__2012_13": 1618153,
      "__2013_14": 1669316
    },
    {
      "category": "Construction",
      "sector": "Construction",
      "__2004_05": 1425971,
      "__2005_06": 1788145,
      "__2006_07": 2129827,
      "__2007_08": 2693304,
      "__2008_09": 2965166,
      "__2009_10": 3082831,
      "__2010_11": 3873002,
      "__2011_12": 4512772,
      "__2012_13": 4876070,
      "__2013_14": 5298291
    },
    {
      "category": "Electricity,gas and Water supply",
      "sector": "Electricity,gas and Water supply",
      "__2004_05": 370448,
      "__2005_06": 445846,
      "__2006_07": 479264,
      "__2007_08": 534564,
      "__2008_09": 444085,
      "__2009_10": 745650,
      "__2010_11": 871434,
      "__2011_12": 996916,
      "__2012_13": 1066383,
      "__2013_14": 1202617
    },
    {
      "category": "Industry",
      "sector": "Total",
      "__2004_05": 5048876,
      "__2005_06": 5804072,
      "__2006_07": 7270090,
      "__2007_08": 8609623,
      "__2008_09": 9724042,
      "__2009_10": 9821917,
      "__2010_11": 11770045,
      "__2011_12": 12911082,
      "__2012_13": 13804933,
      "__2013_14": 14771212
    },
    {
      "category": "Transport,storage & communication",
      "sector": "Total",
      "__2004_05": 1159170,
      "__2005_06": 1317408,
      "__2006_07": 1473020,
      "__2007_08": 1666840,
      "__2008_09": 1959476,
      "__2009_10": 2334533,
      "__2010_11": 2624407,
      "__2011_12": 3203823,
      "__2012_13": 3774551,
      "__2013_14": 4576596
    },
    {
      "category": "Transport,storage & communication",
      "sector": "Railways",
      "__2004_05": 100265,
      "__2005_06": 108463,
      "__2006_07": 130905,
      "__2007_08": 158577,
      "__2008_09": 152007,
      "__2009_10": 168908,
      "__2010_11": 166009,
      "__2011_12": 204420,
      "__2012_13": 228916,
      "__2013_14": 250601
    },
    {
      "category": "Transport,storage & communication",
      "sector": "Transport by other means",
      "__2004_05": 735639,
      "__2005_06": 858893,
      "__2006_07": 978959,
      "__2007_08": 1122143,
      "__2008_09": 1360782,
      "__2009_10": 1620332,
      "__2010_11": 1936713,
      "__2011_12": 2419829,
      "__2012_13": 2878770,
      "__2013_14": 3307186
    },
    {
      "category": "Transport,storage & communication",
      "sector": "Storage",
      "__2004_05": 2976,
      "__2005_06": 3589,
      "__2006_07": 4626,
      "__2007_08": 4777,
      "__2008_09": 4987,
      "__2009_10": 8269,
      "__2010_11": 7593,
      "__2011_12": 9394,
      "__2012_13": 10870,
      "__2013_14": 11408
    },
    {
      "category": "Transport,storage & communication",
      "sector": "Communication",
      "__2004_05": 320291,
      "__2005_06": 346462,
      "__2006_07": 358530,
      "__2007_08": 381342,
      "__2008_09": 441700,
      "__2009_10": 537024,
      "__2010_11": 514092,
      "__2011_12": 570180,
      "__2012_13": 655996,
      "__2013_14": 1007401
    },
    {
      "category": "Trade,hotels and restaurants",
      "sector": "Trade,hotels and restaurants",
      "__2004_05": 2313861,
      "__2005_06": 2847192,
      "__2006_07": 3209902,
      "__2007_08": 3904743,
      "__2008_09": 4377978,
      "__2009_10": 4744384,
      "__2010_11": 5842082,
      "__2011_12": 6175415,
      "__2012_13": 6867492,
      "__2013_14": 7313190
    },
    {
      "category": "Banking & Insurance",
      "sector": "Banking & Insurance",
      "__2004_05": 1021207,
      "__2005_06": 1100446,
      "__2006_07": 1285566,
      "__2007_08": 1511153,
      "__2008_09": 1827914,
      "__2009_10": 1997937,
      "__2010_11": 2271773,
      "__2011_12": 2663942,
      "__2012_13": 3044474,
      "__2013_14": 3526380
    },
    {
      "category": "Real estate,ownership of dwellings and business services",
      "sector": "Real estate,ownership of dwellings and business services",
      "__2004_05": 2159579,
      "__2005_06": 2656062,
      "__2006_07": 3239827,
      "__2007_08": 3955865,
      "__2008_09": 4803937,
      "__2009_10": 5629069,
      "__2010_11": 6650225,
      "__2011_12": 7884549,
      "__2012_13": 9501052,
      "__2013_14": 11543405
    },
    {
      "category": "Public administration",
      "sector": "Public administration",
      "__2004_05": 661552,
      "__2005_06": 731954,
      "__2006_07": 830073,
      "__2007_08": 1002339,
      "__2008_09": 1232246,
      "__2009_10": 1205939,
      "__2010_11": 1359772,
      "__2011_12": 1468805,
      "__2012_13": 1888865,
      "__2013_14": 2100672
    },
    {
      "category": "Other services",
      "sector": "Other services",
      "__2004_05": 1191484,
      "__2005_06": 1303538,
      "__2006_07": 1476567,
      "__2007_08": 1800774,
      "__2008_09": 2182033,
      "__2009_10": 2557835,
      "__2010_11": 3176816,
      "__2011_12": 3878741,
      "__2012_13": 4911072,
      "__2013_14": 6288587
    },
    {
      "category": "Services",
      "sector": "Total",
      "__2004_05": 8506853,
      "__2005_06": 9956600,
      "__2006_07": 11514955,
      "__2007_08": 13841714,
      "__2008_09": 16383583,
      "__2009_10": 18469698,
      "__2010_11": 21925075,
      "__2011_12": 25275275,
      "__2012_13": 29987506,
      "__2013_14": 35348831
    },
    {
      "category": "State domestic product",
      "sector": "Total",
      "__2004_05": 16674713,
      "__2005_06": 19590407,
      "__2006_07": 22723706,
      "__2007_08": 27062879,
      "__2008_09": 31031233,
      "__2009_10": 33755850,
      "__2010_11": 41070316,
      "__2011_12": 45521235,
      "__2012_13": 51910892,
      "__2013_14": 58275364
    }
  ]
}