{
  "created": 1497002340,
  "updated": 1543531898,
  "title": "National Income at factor cost at current prices from 2004-05 to 2013-14",
  "source": "data.gov.in",
  "org_type": "Central",
  "org": [
    "Ministry of Statistics and Programme Implementation"
  ],
  "sector": [
    "Macro Economy",
    "Economy",
    "Statistics"
  ],
  "visualizable": "1",
  "index_name": "503fecf6-a064-490b-a70f-5ed51bbe32a4",
  "catalog_uuid": "86a1bb60-b37e-40a9-abfa-e5e0a862c40b",
  "status": "ok",
  "field": [
    {
      "id": "item",
      "name": "Item",
      "type": "keyword"
    },
    {
      "id": "__2004_05",
      "name": "2004-05",
      "type": "double"
    },
    {
      "id": "__2005_06",
      "name": "2005-06",
      "type": "double"
    },
    {
      "id": "__2006_07",
      "name": "2006-07",
      "type": "double"
    },
    {
      "id": "__2007_08",
      "name": "2007-08",
      "type": "double"
    },
    {
      "id": "__2008_09",
      "name": "2008-09",
      "type": "double"
    },
    {
      "id": "__2009_10",
      "name": "2009-10",
      "type": "double"
    },
    {
      "id": "__2010_11",
      "name": "2010-11",
      "type": "double"
    },
    {
      "id": "__2011_12",
      "name": "2011-12",
      "type": "double"
    },
    {
      "id": "__2012_13",
      "name": "2012-13",
      "type": "double"
    },
    {
      "id": "__2013_14",
      "name": "2013-14",
      "type": "double"
    }
  ],
  "created_date": "2017-06-09T09:59:00Z",
  "updated_date": "2018-11-30T04:21:38Z",
  "active": "1",
  "external_ws_url": "",
  "external_ws": "0",
  "message": "Resource lists",
  "version": "2.2.0",
  "total": 8,
  "count": 8,
  "limit": "999",
  "offset": "0",
  "records": [
    {
      "item": "Gross National Income(GNI)",
      "__2004_05": "2949089",
      "__2005_06": "3364387",
      "__2006_07": "3920042",
      "__2007_08": "4561574",
      "__2008_09": "5270643",
      "__2009_10": "6070903",
      "__2010_11": "7167053",
      "__2011_12": "8314861",
      "__2012_13": "9272110",
      "__2013_14": "10344507"
    },
    {
      "item": "Net National Income(NNI)",
      "__2004_05": "2629198",
      "__2005_06": "3000666",
      "__2006_07": "3501313",
      "__2007_08": "4076878",
      "__2008_09": "4705446",
      "__2009_10": "5411104",
      "__2010_11": "6406834",
      "__2011_12": "7434965",
      "__2012_13": "8255978",
      "__2013_14": "9171045"
    },
    {
      "item": "Estimated Population (Million)",
      "__2004_05": "1089",
      "__2005_06": "1106",
      "__2006_07": "1122",
      "__2007_08": "1138",
      "__2008_09": "1154",
      "__2009_10": "1170",
      "__2010_11": "1186",
      "__2011_12": "1202",
      "__2012_13": "1217",
      "__2013_14": "1233"
    },
    {
      "item": "Per Capita Net National Income (`)",
      "__2004_05": "24143",
      "__2005_06": "27131",
      "__2006_07": "31206",
      "__2007_08": "35825",
      "__2008_09": "40775",
      "__2009_10": "46249",
      "__2010_11": "54021",
      "__2011_12": "61855",
      "__2012_13": "67839",
      "__2013_14": "74380"
    },
    {
      "item": "Index Number(2004-05=100)",
      "__2004_05": "NA",
      "__2005_06": "NA",
      "__2006_07": "NA",
      "__2007_08": "NA",
      "__2008_09": "NA",
      "__2009_10": "NA",
      "__2010_11": "NA",
      "__2011_12": "NA",
      "__2012_13": "NA",
      "__2013_14": "NA"
    },
    {
      "item": "GNI",
      "__2004_05": "100",
      "__2005_06": "114.1",
      "__2006_07": "132.9",
      "__2007_08": "154.7",
      "__2008_09": "178.7",
      "__2009_10": "205.9",
      "__2010_11": "243",
      "__2011_12": "281.9",
      "__2012_13": "314.4",
      "__2013_14": "350.8"
    },
    {
      "item": "NNI",
      "__2004_05": "100",
      "__2005_06": "114.1",
      "__2006_07": "133.2",
      "__2007_08": "155.1",
      "__2008_09": "179",
      "__2009_10": "205.8",
      "__2010_11": "243.7",
      "__2011_12": "282.8",
      "__2012_13": "314",
      "__2013_14": "348.8"
    },
    {
      "item": "Per Capita NNI",
      "__2004_05": "100",
      "__2005_06": "112.4",
      "__2006_07": "129.3",
      "__2007_08": "148.4",
      "__2008_09": "168.9",
      "__2009_10": "191.6",
      "__2010_11": "223.8",
      "__2011_12": "256.2",
      "__2012_13": "281",
      "__2013_14": "308.1"
    }
  ]
}